sqlstar/__init__.py
sqlstar/__version__.py
sqlstar/cmdline.py
sqlstar/core.py
sqlstar/importer.py
sqlstar/interfaces.py
sqlstar/logo.png
sqlstar/py.typed
sqlstar/utils.py
sqlstar/backends/__init__.py
sqlstar/backends/mysql.py
sqlstar/backends/postgre.py
sqlstar-3.2.5.data/data/LICENSE
sqlstar-3.2.5.dist-info/LICENSE
sqlstar-3.2.5.dist-info/METADATA
sqlstar-3.2.5.dist-info/WHEEL
sqlstar-3.2.5.dist-info/entry_points.txt
sqlstar-3.2.5.dist-info/top_level.txt
sqlstar-3.2.5.dist-info/RECORD
