Metadata-Version: 2.1
Name: sqlstar
Version: 3.2.5
Summary: ✨ Awesome databases framework that shines ✨
Home-page: https://github.com/szj2ys/sqlstar
Author: szj
Author-email: szj2ys@qq.com
License: MIT
Classifier: Development Status :: 3 - Alpha
Classifier: License :: OSI Approved :: MIT License
Classifier: Programming Language :: Python :: 3
Requires-Python: >=3.5.0
License-File: LICENSE
Requires-Dist: pandas
Requires-Dist: loguru
Requires-Dist: pymysql
Requires-Dist: psycopg
Requires-Dist: contextvars
Requires-Dist: aiocontextvars
Requires-Dist: toolz
Requires-Dist: click
Requires-Dist: click-help-colors
